imgavg/__init__.py
imgavg/cli.py
imgavg/imgavg.py
imgavg-0.6.dist-info/entry_points.txt
imgavg-0.6.dist-info/LICENSE
imgavg-0.6.dist-info/WHEEL
imgavg-0.6.dist-info/METADATA
imgavg-0.6.dist-info/RECORD
